glik_plugin_local/__init__.py
glik_plugin_local/config/__init__.py
glik_plugin_local/config/config.py
glik_plugin_local/config/logger_format.py
glik_plugin_local/core/__init__.py
glik_plugin_local/core/entities/__init__.py
glik_plugin_local/core/entities/invocation.py
glik_plugin_local/core/entities/message.py
glik_plugin_local/core/entities/plugin/__init__.py
glik_plugin_local/core/entities/plugin/io.py
glik_plugin_local/core/entities/plugin/parameter_type.py
glik_plugin_local/core/entities/plugin/request.py
glik_plugin_local/core/entities/plugin/setup.py
glik_plugin_local/core/plugin_executor.py
glik_plugin_local/core/plugin_registration.py
glik_plugin_local/core/runtime.py
glik_plugin_local/core/server/__base/__init__.py
glik_plugin_local/core/server/__base/filter_reader.py
glik_plugin_local/core/server/__base/request_reader.py
glik_plugin_local/core/server/__base/response_writer.py
glik_plugin_local/core/server/__base/writer_entities.py
glik_plugin_local/core/server/__init__.py
glik_plugin_local/core/server/io_server.py
glik_plugin_local/core/server/router.py
glik_plugin_local/core/server/serverless/__init__.py
glik_plugin_local/core/server/serverless/request_reader.py
glik_plugin_local/core/server/serverless/response_writer.py
glik_plugin_local/core/server/stdio/__init__.py
glik_plugin_local/core/server/stdio/request_reader.py
glik_plugin_local/core/server/stdio/response_writer.py
glik_plugin_local/core/server/tcp/__init__.py
glik_plugin_local/core/server/tcp/request_reader.py
glik_plugin_local/core/utils/__init__.py
glik_plugin_local/core/utils/class_loader.py
glik_plugin_local/core/utils/http_parser.py
glik_plugin_local/core/utils/position_helper.py
glik_plugin_local/core/utils/yaml_loader.py
glik_plugin_local/entities/__init__.py
glik_plugin_local/entities/agent.py
glik_plugin_local/entities/endpoint.py
glik_plugin_local/entities/model/__init__.py
glik_plugin_local/entities/model/llm.py
glik_plugin_local/entities/model/message.py
glik_plugin_local-0.0.2.dist-info/LICENSE
glik_plugin_local-0.0.2.dist-info/METADATA
glik_plugin_local-0.0.2.dist-info/WHEEL
glik_plugin_local-0.0.2.dist-info/RECORD
