Metadata-Version: 2.1
Name: glik_plugin_local
Version: 0.0.2
Summary: Glik Plugin SDK
Home-page: https://github.com/hongthai0101/glik-plugin-sdk.git
License: Apache-2.0
Keywords: glik,plugin,sdk
Author: langgenius
Author-email: hello@glik.ai
Requires-Python: >=3.11
Classifier: License :: OSI Approved :: Apache Software License
Classifier: Programming Language :: Python :: 3
Classifier: Programming Language :: Python :: 3.11
Classifier: Programming Language :: Python :: 3.12
Classifier: Programming Language :: Python :: 3.13
Requires-Dist: Flask (>=3.0.3,<3.1.0)
Requires-Dist: Werkzeug (>=3.0.3,<3.1.0)
Requires-Dist: dpkt (>=1.9.8,<1.10.0)
Requires-Dist: gevent (>=24.11.1,<24.12.0)
Requires-Dist: httpx (>=0.27.0,<0.28.0)
Requires-Dist: pydantic (>=2.8.2)
Requires-Dist: pydantic-settings (>=2.3.4,<2.4.0)
Requires-Dist: pydub (>=0.25.1,<0.26.0)
Requires-Dist: pyyaml (>=6.0.1,<6.1.0)
Requires-Dist: requests (>=2.32.3,<2.33.0)
Requires-Dist: socksio (==1.0.0)
Requires-Dist: tiktoken (>=0.8.0,<0.9.0)
Requires-Dist: yarl (>=1.9.4,<2.0)
